zodchy_patterns/__init__.py
zodchy_patterns/events/__init__.py
zodchy_patterns/events/io/__init__.py
zodchy_patterns/events/io/error.py
zodchy_patterns/events/io/generic.py
zodchy_patterns/events/io/info.py
zodchy_patterns/mapping.py
zodchy_patterns-0.3.4.dist-info/METADATA
zodchy_patterns-0.3.4.dist-info/WHEEL
zodchy_patterns-0.3.4.dist-info/RECORD
