Metadata-Version: 2.1
Name: zodchy-patterns
Version: 0.3.4
Summary: Collection of patterns to use in CQRS applications
Home-page: https://github.com/smairon/zodchy-patterns
Author: Smairon
Author-email: man@smairon.ru
Requires-Python: >=3.11,<4.0
Classifier: Programming Language :: Python :: 3
Classifier: Programming Language :: Python :: 3.11
Classifier: Programming Language :: Python :: 3.12
Requires-Dist: zodchy (>=0.5.0,<0.6.0)
Project-URL: Repository, https://github.com/smairon/zodchy-patterns
